dagre_py/__init__.py
dagre_py/core.py
dagre_py/js/d3.v5.min.js
dagre_py/js/dagre-d3.min.js
dagre_py/js/index.html
dagre_py/js/script.js
dagre_py/js/style.css
dagre_py/js/tippy.all.min.js
dagre_py-0.1.7.dist-info/LICENSE
dagre_py-0.1.7.dist-info/METADATA
dagre_py-0.1.7.dist-info/WHEEL
dagre_py-0.1.7.dist-info/RECORD
